py_i2c_register
