Metadata-Version: 1.1
Name: py-i2c-register
Version: 0.0.8
Summary: Python wrapper library around the common I2C controller register pattern.
Home-page: https://github.com/Noah-Huppert/py-i2c-register
Author: Noah Huppert
Author-email: developer.noah@gmail.com
License: MIT
Keywords: library i2c registers
Platform: UNKNOWN
Classifier: Development Status :: 3 - Alpha
Classifier: Intended Audience :: Developers
Classifier: Topic :: Software Development :: Libraries :: Python Modules
Classifier: Programming Language :: Python :: 2
Classifier: Programming Language :: Python :: 3
